pycreg.cp39-win_amd64.pyd
libcreg_python-20240419.dist-info/METADATA
libcreg_python-20240419.dist-info/WHEEL
libcreg_python-20240419.dist-info/top_level.txt
libcreg_python-20240419.dist-info/RECORD
