Metadata-Version: 2.1
Name: libcreg-python
Version: 20240419
Summary: Python bindings module for libcreg
Author: Joachim Metz
Author-email: joachim.metz@gmail.com
License: GNU Lesser General Public License v3 or later (LGPLv3+)
Classifier: Development Status :: 2 - Pre-Alpha
Classifier: Programming Language :: Python
Requires-Python: >=3.7
